worstcase/__init__.py
worstcase/worstcase.py
worstcase-0.5.0.dist-info/LICENSE
worstcase-0.5.0.dist-info/METADATA
worstcase-0.5.0.dist-info/WHEEL
worstcase-0.5.0.dist-info/RECORD
