Metadata-Version: 2.1
Name: worstcase
Version: 0.5.0
Summary: Worst case analysis and sensitivity studies. Extreme Value, Root-Sum-Square, Monte Carlo.
Home-page: https://github.com/amosborne/worstcase
License: MIT
Author: amosborne
Author-email: amosborne@users.noreply.github.com
Requires-Python: >=3.9,<4.0
Classifier: License :: OSI Approved :: MIT License
Classifier: Programming Language :: Python :: 3
Classifier: Programming Language :: Python :: 3.9
Classifier: Programming Language :: Python :: 3.10
Classifier: Programming Language :: Python :: 3.11
Requires-Dist: Pint (>=0.20,<0.21)
Requires-Dist: networkx (>=2.5.1,<3.0.0)
Requires-Dist: pyDOE (>=0.3.8,<0.4.0)
Project-URL: Repository, https://github.com/amosborne/worstcase
